{
  "$schema": "https://developer.microsoft.com/json-schemas/spfx-build/package-solution.schema.json",
  "solution": {
    "name": "practice-client-side-solution",
    "id": "d2f27cd0-df16-44fc-a669-8857261a0d1a",
    "version": "1.0.0.0",
    "includeClientSideAssets": true,
    "skipFeatureDeployment": true,

    "webApiPermissionRequests": [
      {
        "resource": "Microsoft Graph",
        "scope": "Sites.ReadWrite.All"
      },
      {
        "resource": "Microsoft Graph",
        "scope": "User.ReadWrite.All"
      }
    ],

    "isDomainIsolated": false,
    "developer": {
      "name": "",
      "websiteUrl": "",
      "privacyUrl": "",
      "termsOfUseUrl": "",
      "mpnId": "Undefined-1.17.4"
    },
    "metadata": {
      "shortDescription": {
        "default": "practice description"
      },
      "longDescription": {
        "default": "practice description"
      },
      "screenshotPaths": [],
      "videoUrl": "",
      "categories": []
    },
    "features": [
      {
        "title": "practice Feature",
        "description": "The feature that activates elements of the practice solution.",
        "id": "fb23443b-7441-4895-aaca-4510b1a88654",
        "version": "1.0.0.0"
      }
    ]
  },
  "paths": {
    "zippedPackage": "solution/practice.sppkg"
  }
}
